{"tiles": {"92,50": {"grass_gid": 0, "soil_gid": 9}, "94,49": {"grass_gid": 0, "soil_gid": 3}, "97,49": {"grass_gid": 0, "soil_gid": 3}, "99,49": {"grass_gid": 0, "soil_gid": 3}, "100,49": {"grass_gid": 0, "soil_gid": 3}, "102,49": {"grass_gid": 0, "soil_gid": 3}, "94,53": {"grass_gid": 0, "soil_gid": 3}, "94,54": {"grass_gid": 0, "soil_gid": 3}, "94,56": {"grass_gid": 0, "soil_gid": 3}, "61,59": {"grass_gid": 0, "soil_gid": 7}, "57,63": {"grass_gid": 0, "soil_gid": 3}, "38,66": {"grass_gid": 0, "soil_gid": 6}, "40,66": {"grass_gid": 0, "soil_gid": 3}, "37,66": {"grass_gid": 0, "soil_gid": 7}, "39,66": {"grass_gid": 0, "soil_gid": 3}, "38,65": {"grass_gid": 0, "soil_gid": 3}, "38,67": {"grass_gid": 0, "soil_gid": 3}, "38,68": {"grass_gid": 0, "soil_gid": 3}, "66,61": {"grass_gid": 0, "soil_gid": 6}, "76,52": {"grass_gid": 0, "soil_gid": 3}, "82,57": {"grass_gid": 0, "soil_gid": 3}, "81,57": {"grass_gid": 0, "soil_gid": 3}, "79,57": {"grass_gid": 0, "soil_gid": 3}, "78,57": {"grass_gid": 0, "soil_gid": 6}, "80,57": {"grass_gid": 0, "soil_gid": 3}, "79,58": {"grass_gid": 0, "soil_gid": 3}, "79,59": {"grass_gid": 0, "soil_gid": 6}, "81,58": {"grass_gid": 0, "soil_gid": 3}, "81,59": {"grass_gid": 0, "soil_gid": 3}, "81,60": {"grass_gid": 0, "soil_gid": 3}, "78,61": {"grass_gid": 0, "soil_gid": 3}, "79,60": {"grass_gid": 0, "soil_gid": 3}, "77,54": {"grass_gid": 0, "soil_gid": 3}, "74,62": {"grass_gid": 0, "soil_gid": 3}, "79,62": {"grass_gid": 0, "soil_gid": 6}, "87,54": {"grass_gid": 0, "soil_gid": 3}, "66,58": {"grass_gid": 0, "soil_gid": 3}}, "plants": {}}